xia_broadcast/__init__.py
xia_broadcast/broadcast.cp310-win_amd64.pyd
xia_broadcast-0.1.5.dist-info/LICENSE.txt
xia_broadcast-0.1.5.dist-info/METADATA
xia_broadcast-0.1.5.dist-info/WHEEL
xia_broadcast-0.1.5.dist-info/top_level.txt
xia_broadcast-0.1.5.dist-info/RECORD
