Metadata-Version: 2.1
Name: xia-broadcast
Version: 0.1.5
Home-page: https://develop.x-i-a.com/docs/xia-broadcast/0.1.5/index.html
Author: X-I-A
Author-email: admin@x-i-a.com
Requires-Python: >=3.9
License-File: LICENSE.txt
Requires-Dist: requests
Requires-Dist: xia-engine
